[{
    "name": "UI Graphics",
    "list": [{
        "Website": "UI Design Daily",
        "Description": "Awesome UI Components of all types",
        "url": "https://uidesigndaily.com/"
      },
      {
        "Website": "100 Daily UI",
        "Description": "Free Figma library of products, elements, and screens",
        "url": "https://100dailyui.webflow.io/"
      },
      {
        "Website": "Sketch App\\n Sources",
        "Description": "Sketch UIs, wireframes, icons and much more",
        "url": "https://www.sketchappsources.com/"
      },
      {
        "Website": "Humaaans",
        "Description": "Cool illustrations of people with the ability to mix and match",
        "url": "https://www.humaaans.com/"
      },
      {
        "Website": "Paaatterns",
        "Description": "Free collection of beautiful patterns for all vector formats",
        "url": "https://products.ls.graphics/paaatterns/"
      },
      {
        "Website": "thepatternlibrary",
        "Description": "Free beautiful background patterns",
        "url": "http://thepatternlibrary.com/"
      },
      {
        "Website": "404 illustration",
        "Description": "free illustrations for 404 pages",
        "url": "https://error404.fun/"
      },
      {
        "Website": "Drawkit.io",
        "Description": "Illustrations for designers and startups",
        "url": "https://www.drawkit.io/"
      },
      {
        "Website": "Undraw.co",
        "Description": "Open-source illustrations for any idea you can imagine and create",
        "url": "https://undraw.co/"
      },
      {
        "Website": "Illustration.co",
        "Description": "Open-source illustrations kit",
        "url": "https://illlustrations.co/"
      },
      {
        "Website": "Manypixels.co",
        "Description": "Monochromatic, Isometric high quality illustrations",
        "url": "https://www.manypixels.co/gallery/"
      },
      {
        "Website": "Opendoodles",
        "Description": "Free sketchy illustrations",
        "url": "https://www.opendoodles.com/"
      },
      {
        "Website": "Open Peeps",
        "Description": "Hand drawn illustration library",
        "url": "https://www.openpeeps.com/"
      },
      {
        "Website": "UI Space",
        "Description": "Thousands of great UI freebies",
        "url": "https://uispace.net/"
      },
      {
        "Website": "Animations.co",
        "Description": "Beautiful, customizable animated GIF icons",
        "url": "http://animaticons.co/"
      },
      {
        "Website": "Uplabs",
        "Description": "High-quality design resources (Free & Premium)",
        "url": "https://www.uplabs.com/"
      },
      {
        "Website": "InvisionApp",
        "Description": "Library of free, high-quality UI kits, icon packs, and mockups",
        "url": "https://www.invisionapp.com/inside-design/design-resources/"
      },
      {
        "Website": "Open Doodles",
        "Description": "A Free Set of Sketchy Illustrations",
        "url": "https://www.opendoodles.com/"
      },
      {
        "Website": "Avataaars",
        "Description": "Free sketch library of avatars illustrations by Pablo Stanley",
        "url": "https://avataaars.com/"
      },
      {
        "Website": "FreebieSketch",
        "Description": "Free Sketch designs, wireframes, illustrations, and more.",
        "url": "https://freebiesketch.com/"
      },
      {
        "Website": "Blush",
        "Description": "Free customizable illustrations with Figma Plugin",
        "url": "https://blush.design/"
      },
      {
        "Website": "Hero Patterns",
        "Description": "A collection of repeatable SVG background patterns",
        "url": "http://www.heropatterns.com/"
      }
    ]
  },
  {
    "name": "Fonts",
    "list": [{
        "Website": "Google Fonts",
        "Description": "Library of around 1000 free licensed font families",
        "url": "https://fonts.google.com/"
      },
      {
        "Website": "DaFont",
        "Description": "Archive of freely downloadable fonts",
        "url": "https://www.dafont.com/"
      },
      {
        "Website": "Use & Modify",
        "Description": "Personal selection of beautiful, classy, punk, professional, incomplete, weird typefaces",
        "url": "https://usemodify.com/"
      },
      {
        "Website": "1001 Free Fonts",
        "Description": "I think the name speaks for itself",
        "url": "https://www.1001freefonts.com/"
      },
      {
        "Website": "Font Squirrel",
        "Description": "Font Squirrel scours the internet for high quality, legitimately free fonts",
        "url": "https://www.fontsquirrel.com/"
      },
      {
        "Website": "Font\\n Fabric",
        "Description": "A digital type foundry crafting retail fonts and custom typography for various brands",
        "url": "https://www.fontfabric.com/free-fonts/"
      },
      {
        "Website": "What\\n Font",
        "Description": "Tool for finding the fonts of a website without having to search in the devtools",
        "url": "http://www.chengyinliu.com/whatfont.html"
      },
      {
        "Website": "Tiff",
        "Description": "A type diff tool that visually contrasts the differences between two fonts",
        "url": "https://tiff.herokuapp.com/"
      },
      {
        "Website": "Font Flame",
        "Description": "Tool for pairing fonts to see how they look together",
        "url": "http://app.fontflame.com/"
      },
      {
        "Website": "TypeKit Practice",
        "Description": "Learn about typography practices",
        "url": "https://practice.typekit.com/"
      },
      {
        "Website": "Fontjoy",
        "Description": "Generate font pairing in one click",
        "url": "https://fontjoy.com/"
      },
      {
        "Website": "Golden Ratio",
        "Description": "Golden Ratio Typography Calculator",
        "url": "https://grtcalculator.com/"
      },
      {
        "Website": "FontSpark",
        "Description": "Discover Better Fonts",
        "url": "https://fontspark.app/"
      },
      {
        "Website": "FontPair",
        "Description": "Helps you pair Google Fonts together",
        "url": "https://fontpair.co/"
      },
      {
        "Website": "Font Space",
        "Description": "A designer-centered free font website that has quick customizable previews",
        "url": "https://www.fontspace.com/"
      },
      {
        "Website": "Abstract Fonts",
        "Description": "Fonts free for personal and commercial use",
        "url": "http://www.abstractfonts.com/"
      },
      {
        "Website": "Free Typography",
        "Description": "A list of high quality fonts",
        "url": "https://freetypography.com/"
      },
      {
        "Website": "Leon Sans",
        "Description": "A geometric sans-serif typeface made with code",
        "url": "https://github.com/cmiscm/leonsans/"
      },
      {
        "Website": "Lexend",
        "Description": "A variable font empirically shown to significantly improve reading-proficiency",
        "url": "https://www.lexend.com/"
      },
      {
        "Website": "Fonts for Apple\\n Platforms",
        "Description": "Get the details, frameworks, and tools you need to use system fonts for Apple platforms in\\n your apps",
        "url": "https://developer.apple.com/fonts/"
      },
      {
        "Website": "SFWin",
        "Description": "San Francisco Fonts for Windows 10 and non-Apple Platform",
        "url": "https://github.com/blaisck/sfwin/"
      },
      {
        "Website": "Font Flipper",
        "Description": "Preview 800+ Google Fonts on top of your own designs, without having to download the fonts",
        "url": "https://fontflipper.com/"
      },
      {
        "Website": "Fonts Arena",
        "Description": "Free curated fonts",
        "url": "https://fontsarena.com/"
      },
      {
        "Website": "Befonts",
        "Description": "High quality fonts for free",
        "url": "https://befonts.com/"
      },
      {
        "Website": "Arabic fonts",
        "Description": "Arabic fonts for free",
        "url": "https://arabicfonts.net/"
      },
      {
        "Website": "FontDrop",
        "Description": "Simple and easy way to view the contents of font files",
        "url": "https://fontdrop.info"
      }
    ]
  },
  {
    "name": "Icons",
    "list": [{
        "Website": "UXWing",
        "Description": "Well Optimized, Free icons for commercial use",
        "url": "https://uxwing.com/"
      },
      {
        "Website": "Shapedfonts\\n Iconclub",
        "Description": "8000+ free icons",
        "url": "https://shapedfonts.com/iconclub/"
      },
      {
        "Website": "Feather Icons",
        "Description": "Beautiful, customizable open source icons",
        "url": "https://feathericons.com/"
      },
      {
        "Website": "Tabler Icons",
        "Description": "470+ highly customizable open source SVG icons",
        "url": "https://tablericons.com/"
      },
      {
        "Website": "Simple Icons",
        "Description": "1307 Free SVG icons for popular brands",
        "url": "https://simpleicons.org/"
      },
      {
        "Website": "Instant Logo Search",
        "Description": "thousands of free brands logos ( SVG - PNG )",
        "url": "http://instantlogosearch.com/"
      },
      {
        "Website": "Linear Icons",
        "Description": "1000+ Ultra crisp vector icons",
        "url": "https://linearicons.com/free"
      },
      {
        "Website": "Entypo",
        "Description": "411 carefully crafted premium pictograms by Daniel Bruce",
        "url": "http://www.entypo.com/"
      },
      {
        "Website": "Icons8",
        "Description": "Free icons, photos, vectors and tools",
        "url": "https://icons8.com/"
      },
      {
        "Website": "Flat Icon",
        "Description": "The largest database of free icons in PNG, SVG, EPS, PSD and BASE 64 formats",
        "url": "https://www.flaticon.com/"
      },
      {
        "Website": "The Noun Project",
        "Description": "Over 2 Million curated icons, created by a global community",
        "url": "https://thenounproject.com/"
      },
      {
        "Website": "Iconscout",
        "Description": "Free Download Icons illustrations stock photos at one place",
        "url": "https://iconscout.com/"
      },
      {
        "Website": "Nucleo App",
        "Description": "Nucleo is a beautiful library of 27500 icons, and a powerful application to collect, customize\\n and export all your icons. (Free & Paid)",
        "url": "https://nucleoapp.com/"
      },
      {
        "Website": "Icon-icons.com",
        "Description": "Free Icons PNG, ICO, ICNS and Vector file SVG",
        "url": "https://icon-icons.com/"
      },
      {
        "Website": "Bootstrap Icons",
        "Description": "Free Icons built for Bootstrap but they'll work in any project",
        "url": "https://icons.getbootstrap.com/"
      },
      {
        "Website": "Remix Icon",
        "Description": "Simply Delightful Icon System",
        "url": "https://remixicon.com/"
      },
      {
        "Website": "Iconmonstr",
        "Description": "Discover 4496+ free icons in 313 collections",
        "url": "https://iconmonstr.com/"
      },
      {
        "Website": "Vivid.js",
        "Description": "Ready to use Free and Open Source SVG Icons Pack JavaScript Library.",
        "url": "https://webkul.github.io/vivid/"
      },
      {
        "Website": "Iconfinder",
        "Description": "Free and premium vector icons in SVG, PNG, CSH and AI format",
        "url": "https://www.iconfinder.com/"
      },
      {
        "Website": "Lordicon",
        "Description": "50 free animated interactive icons",
        "url": "https://lordicon.com/free-icons"
      },
      {
        "Website": "UseAnimations",
        "Description": "Free Animated Icons in SVG and Json Format(for lottie)",
        "url": "https://useanimations.com/"
      },
      {
        "Website": "css.gg",
        "Description": "700+ Open-source CSS, SVG and Figma UI Icons Available in SVG Sprite, styled-components, NPM\\n & API",
        "url": "https://css.gg/"
      },
      {
        "Website": "SVGPorn",
        "Description": "1000+ high-quality SVG logos",
        "url": "https://svgporn.com"
      },
      {
        "Website": "Payment System Logos",
        "Description": "Logos for payment systems available in png and svg",
        "url": "https://github.com/mpay24/payment-logos/"
      },
      {
        "Website": "Browser Logos",
        "Description": "High resolution web browser logos",
        "url": "https://github.com/alrra/browser-logos/"
      },
      {
        "Website": "IconBros",
        "Description": "7843+ free icons grouped in 182 collections",
        "url": "https://www.iconbros.com"
      },
      {
        "Website": "LogoHub",
        "Description": "Generate and download your logo for free in PNG and SVG format",
        "url": "https://logohub.io/"
      },
      {
        "Website": "Material Design\\n Icons",
        "Description": "A icon collection allowing designers and developers targeting various platforms to download\\n icons in the format, color and size they need for any project.",
        "url": "https://materialdesignicons.com/"
      },
      {
        "Website": "Heroicons",
        "Description": "Free, open source icons from the creators of Tailwind CSS.",
        "url": "https://heroicons.dev/"
      },
      {
        "Website": "Zondicons",
        "Description": "A set of free premium SVG icons for you to use on your digital products.",
        "url": "https://www.zondicons.com/icons.html"
      },
      {
        "Website": "Endless Icons",
        "Description": "A website offering a number of free icons. Icons are tagged and also compressed into kits.",
        "url": "http://endlessicons.com/"
      },
      {
        "Website": "Icomoon",
        "Description": "Browse 5500+ Free Icons. Add any set you wish to easily browse and search its icons.",
        "url": "https://icomoon.io/app/"
      },
      {
        "Website": "Eva Icons",
        "Description": "Eva Icons is a pack of more than 480 beautifully crafted Open Source icons for common actions\\n and items.",
        "url": "https://akveo.github.io/eva-icons/#/"
      },
      {
        "Website": "Zondicons",
        "Description": "A set of free premium SVG icons for you to use on your digital products. you can download the\\n icons into your desktop",
        "url": "http://www.zondicons.com/"
      },
      {
        "Website": "Entypo",
        "Description": "411 carefully crafted premium pictograms",
        "url": "http://www.entypo.com/"
      },
      {
        "Website": "Cryptoicons",
        "Description": "A set of 430 crypto and fiat currency icons. Completely free.",
        "url": "http://cryptoicons.co/"
      },
      {
        "Website": "Ikonate",
        "Description": "Fully customisable & accessible vector icons",
        "url": "https://ikonate.com/"
      },
      {
        "Website": "appicon",
        "Description": "Quickly generate app icons in diffrent sizes for your IOS, macOS and Android projects",
        "url": "https://appicon.co/"
      },
      {
        "Website": "LineIcons",
        "Description": "2000+ Essential Line Icons for Designers and Developers",
        "url": "https://lineicons.com"
      }
    ]
  },
  {
    "name": "Favicons",
    "list": [{
        "Website": "Favicon.io",
        "Description": "Generate a favicon from text, from an image, or from an emoji. Download in .ico and .png\\n formats",
        "url": "https://favicon.io/"
      },
      {
        "Website": "Favicon\\n Generator",
        "Description": "Generate favicon ico files for your website",
        "url": "http://tools.dynamicdrive.com/favicon/"
      },
      {
        "Website": "RealFaviconGenerator",
        "Description": "Generate icons for all platforms (Windows, iOS, Android)",
        "url": "https://realfavicongenerator.net/"
      },
      {
        "Website": "FontIcon",
        "Description": "Generate favicons and images from Font Awesome icons",
        "url": "https://gauger.io/fonticon/"
      }
    ]
  },
  {
    "name": "Icon Fonts",
    "list": [{
        "Website": "Font Awesome",
        "Description": "The web's most popular icon set and toolkit",
        "url": "https://fontawesome.com/"
      },
      {
        "Website": "Line Awesome",
        "Description": "Swap in replacement of Font Awesome with modern line icons",
        "url": "https://icons8.com/line-awesome"
      },
      {
        "Website": "Material\\n Icons",
        "Description": "Material design icon library",
        "url": "https://material.io/resources/icons/"
      },
      {
        "Website": "IonIcons",
        "Description": "Beautifully crafted open source icons from Ionic team",
        "url": "http://ionicons.com/"
      },
      {
        "Website": "Zurb Foundation\\n Icons",
        "Description": "Customizable Foundation icons",
        "url": "https://zurb.com/playground/foundation-icon-fonts-3"
      },
      {
        "Website": "Fontisto Icons",
        "Description": "Fontisto the iconic font and css toolkit · 616+ free icons",
        "url": "https://fontisto.com/"
      },
      {
        "Website": "Boxicons",
        "Description": "Boxicons is a free collection of carefully crafted open source icons",
        "url": "https://boxicons.com/"
      },
      {
        "Website": "Icofont",
        "Description": "2100+ free icons to spice up your creative designs",
        "url": "https://icofont.com/"
      },
      {
        "Website": "Material\\n Palette",
        "Description": "Free to pick palettes, icons and colors for Material Design]",
        "url": "https://www.materialpalette.com/icons"
      },
      {
        "Website": "Material Design Iconic Font",
        "Description": "Material design icon font",
        "url": "http://zavoloklom.github.io/material-design-iconic-font/index.html"
      },
      {
        "Website": "Vscode\\n Codicons",
        "Description": "The icon font from Visual Studio Code",
        "url": "https://microsoft.github.io/vscode-codicons/dist/codicon.html"
      },
      {
        "Website": "Devicon",
        "Description": "Devicon is a set of icons representing programming languages, designing & development\\n tools",
        "url": "https://konpa.github.io/devicon/"
      },
      {
        "Website": "PaymentFont",
        "Description": "A sleek webfont for payment operators and methods. Featuring 116 icons",
        "url": "https://paymentfont.com/"
      },
      {
        "Website": "Weather\\n Icons",
        "Description": "Weather Icons is the only icon font with 222 weather themed icons",
        "url": "https://erikflowers.github.io/weather-icons/"
      },
      {
        "Website": "Stroke\\n 7",
        "Description": "202 thin stroke icons inspired by iOS 7",
        "url": "https://themes-pixeden.com/font-demos/7-stroke/index.html"
      },
      {
        "Website": "Jam Icons",
        "Description": "890+ handcrafted icons to make your web app awesome",
        "url": "https://jam-icons.com/"
      },
      {
        "Website": "Fontastic.me",
        "Description": "Create your custom icon fonts in seconds. Over 9,000 icons available to pick from or upload\\n your custom svg",
        "url": "http://fontastic.me/"
      },
      {
        "Website": "Fontello",
        "Description": "200+ web icons where you can customize the names or codes of icons.",
        "url": "http://fontello.com/"
      },
      {
        "Website": "Linea",
        "Description": "Linea: Featuring 750+ Free Icons",
        "url": "https://linea.io/"
      }
    ]
  },
  {
    "name": "Stock Photos",
    "list": [{
        "Website": "Pexels",
        "Description": "Free stock photos shared by talented creators",
        "url": "https://www.pexels.com/"
      },
      {
        "Website": "Unsplash",
        "Description": "The internet’s source of freely usable images",
        "url": "https://unsplash.com/"
      },
      {
        "Website": "Pixabay",
        "Description": "Over 1.7 million+ high quality stock images and videos",
        "url": "https://pixabay.com/"
      },
      {
        "Website": "Magdeleine",
        "Description": "Gallery & free high res photo everyday",
        "url": "https://magdeleine.co/"
      },
      {
        "Website": "Picspree",
        "Description": "Royalty free images, stock photos, illustrations, and vectors",
        "url": "https://picspree.com"
      },
      {
        "Website": "Burst",
        "Description": "Free stock photos collections",
        "url": "https://burst.shopify.com/"
      },
      {
        "Website": "Gratisography",
        "Description": "Free collection of free high-resolution pictures",
        "url": "https://gratisography.com/"
      },
      {
        "Website": "Life of Pix",
        "Description": "Free high resolution photography",
        "url": "https://www.lifeofpix.com/"
      },
      {
        "Website": "Stock Snap",
        "Description": "Hundreds of high quality photos added weekly",
        "url": "https://stocksnap.io/"
      },
      {
        "Website": "Morguefile",
        "Description": "Over 350,000 free stock photos for commercial use",
        "url": "https://morguefile.com/"
      },
      {
        "Website": "Kaboom Pics",
        "Description": "Stock photography and color palettes. Good for product images",
        "url": "https://kaboompics.com/"
      },
      {
        "Website": "New Old Stock",
        "Description": "Stock vintage photos",
        "url": "https://nos.twnsnd.co/"
      },
      {
        "Website": "Pic Jumbo",
        "Description": "Good collections of different types of photos",
        "url": "https://picjumbo.com/"
      },
      {
        "Website": "Public\\n Domain Pictures",
        "Description": "Public domain images of all types",
        "url": "https://www.publicdomainpictures.net/en/"
      },
      {
        "Website": "Find A\\n Photo",
        "Description": "Searches multiple stock photo websites",
        "url": "https://www.chamberofcommerce.org/findaphoto/"
      },
      {
        "Website": "Stockvault",
        "Description": "Categorized stock photos",
        "url": "http://www.stockvault.net/"
      },
      {
        "Website": "Placeholder",
        "Description": "A free image placeholder service for the web. You can specify image size and format",
        "url": "https://placeholder.com/"
      },
      {
        "Website": "Realistic Shots",
        "Description": "Free high resolution stock photos",
        "url": "https://realisticshots.com/"
      },
      {
        "Website": "Negative Space",
        "Description": "High-Resolution Free Stock Photos",
        "url": "https://negativespace.co/"
      },
      {
        "Website": "SkitterPhoto",
        "Description": "Free high resolution photography",
        "url": "https://skitterphoto.com/"
      },
      {
        "Website": "PicoGraphy",
        "Description": "Gorgeous, High-Resolution, Free Photos",
        "url": "https://picography.co/"
      },
      {
        "Website": "Wunder Stock",
        "Description": "Stunningly amazing free photos",
        "url": "https://wunderstock.com/"
      },
      {
        "Website": "PxHere",
        "Description": "Free Images & Free stock photos - PxHere",
        "url": "https://pxhere.com/"
      },
      {
        "Website": "Piqsels",
        "Description": "Royalty Free Stock Photos",
        "url": "https://piqsels.com/"
      },
      {
        "Website": "FoodiesFeed",
        "Description": "Food photo stock",
        "url": "https://www.foodiesfeed.com/"
      },
      {
        "Website": "Nappy",
        "Description": "A website offering Beautiful, high-res photos of black and brown people.",
        "url": "https://www.nappy.co/"
      },
      {
        "Website": "Generated Photos",
        "Description": "Unique AI Generated model photos",
        "url": "https://generated.photos/"
      }
    ]
  },
  {
    "name": "Stock Videos",
    "list": [{
        "Website": "Pexels",
        "Description": "Largest library of free to use videos, donated by the community",
        "url": "https://www.pexels.com/videos"
      },
      {
        "Website": "Pixabay",
        "Description": "Large library of free to use videos, donated by the community similar to Pexels",
        "url": "https://www.pixabay.com/videos"
      },
      {
        "Website": "Coverr.co",
        "Description": "Beautiful free stock video footage",
        "url": "https://coverr.co/"
      },
      {
        "Website": "Videezy",
        "Description": "Free HD stock footage & 4K videos",
        "url": "https://www.videezy.com/"
      },
      {
        "Website": "Mix Kit",
        "Description": "Stock video clips & music",
        "url": "https://mixkit.co/"
      },
      {
        "Website": "Life Of Vids",
        "Description": "Free video clips and loops",
        "url": "https://www.lifeofvids.com/"
      },
      {
        "Website": "Videvo",
        "Description": "Free and premium stock videos",
        "url": "https://www.videvo.net/stock-video-footage/"
      }
    ]
  },
  {
    "name": "Stock Music & Sound Effects ",
    "list": [{
        "Website": "Free Stock\\n Music",
        "Description": "Royalty free stock music for YouTube videos, podcasts, etc",
        "url": "https://www.free-stock-music.com/"
      },
      {
        "Website": "Bensound",
        "Description": "Download Royalty Free Music for free and use it in your project",
        "url": "https://www.bensound.com/"
      },
      {
        "Website": "Mixkit",
        "Description": "Free music for your projects",
        "url": "https://mixkit.co/free-stock-music/"
      },
      {
        "Website": "Freesound",
        "Description": "Free stock music and sounds",
        "url": "https://freesound.org/"
      },
      {
        "Website": "Free Music Archive",
        "Description": "Collaborative database of creative-commons licensed sound for musicians and sound lovers",
        "url": "https://freemusicarchive.org/"
      },
      {
        "Website": "Musopen",
        "Description": "An online copyright free classical music library",
        "url": "https://musopen.org/music/"
      },
      {
        "Website": "Unminus",
        "Description": "Free Premium Music for Your Projects gift Royalty Free. Cleared for YouTube.",
        "url": "https://www.unminus.com/"
      }
    ]
  },
  {
    "name": "Vectors & Clip Art ",
    "list": [{
        "Website": "Vecteezy",
        "Description": "Find and download free vector art",
        "url": "https://www.vecteezy.com/"
      },
      {
        "Website": "Freepik",
        "Description": "Free vectors, stock photos, PSD and icons",
        "url": "https://www.freepik.com"
      },
      {
        "Website": "Free Vectors",
        "Description": "Community of vector lovers who share free vector graphics",
        "url": "https://www.freevectors.net/"
      },
      {
        "Website": "PNGTree",
        "Description": "png, backgrounds, templates, text effects",
        "url": "https://pngtree.com/free-vectors"
      },
      {
        "Website": "Vector4Free",
        "Description": "Free vector graphics",
        "url": "https://www.vector4free.com/"
      },
      {
        "Website": "Retro Vectors",
        "Description": "Vintage vectors and graphics",
        "url": "http://retrovectors.com/"
      },
      {
        "Website": "Freeble",
        "Description": "Vectors, patterns, mockups and more",
        "url": "http://freebbble.com/"
      },
      {
        "Website": "Lukaszadam",
        "Description": "Free Vector atrworks",
        "url": "https://lukaszadam.com/"
      },
      {
        "Website": "Illlustrations",
        "Description": "Beautiful 100 Illustrations - png, svg",
        "url": "https://illlustrations.co/"
      },
      {
        "Website": "Clipart",
        "Description": "Choose great clipart, png, coloring pages, drawings and more for your projects from the free\\n collection!",
        "url": "https://www.clipart.email/"
      },
      {
        "Website": "Growwwkit\\n illustrations",
        "Description": "A set of 8 simple, black & white, stylish illustrations",
        "url": "https://growwwkit.com/illustrations/phonies"
      },
      {
        "Website": "World Vector Logo",
        "Description": "Download vector logos of brands you love",
        "url": "https://worldvectorlogo.com/"
      },
      {
        "Website": "trianglify.io",
        "Description": "Generate low-poly backgrounds, textures, and vectors",
        "url": "https://trianglify.io/"
      },
      {
        "Website": "blob",
        "Description": "Generate Blob shapes for Web and Flutter apps",
        "url": "https://blobs.app/"
      },
      {
        "Website": "HiClipart",
        "Description": "A community for designers to share & download transparent background PNG cliparts",
        "url": "https://www.hiclipart.com/"
      }
    ]
  },
  {
    "name": "Product & Image Mockups ",
    "list": [{
        "Website": "Smart Mockups",
        "Description": "Create stunning product mockups (free & premium)",
        "url": "https://smartmockups.com/"
      },
      {
        "Website": "Shot Snap",
        "Description": "Create beautiful device mockup images for your app or website design",
        "url": "https://shotsnapp.com/"
      },
      {
        "Website": "Screely",
        "Description": "Instantly turn your screenshot into a mockup",
        "url": "https://www.screely.com/"
      },
      {
        "Website": "Screen Peak",
        "Description": "Create a mockup from a URL",
        "url": "https://screenpeek.io/"
      },
      {
        "Website": "Mockup World",
        "Description": "The biggest source of free photo-realistic Mockups online",
        "url": "https://www.mockupworld.co/"
      },
      {
        "Website": "Collab Shot",
        "Description": "Real-time screen grabs and image sharing",
        "url": "https://www.collabshot.com/"
      },
      {
        "Website": "Facebook Devices",
        "Description": "Images and Sketch files of popular devices",
        "url": "https://facebook.design/devices"
      },
      {
        "Website": "Threed.io",
        "Description": "Generate 3D mockups right in your browser.",
        "url": "https://threed.io"
      },
      {
        "Website": "Mockuphone",
        "Description": "100% free mockups for all devices including IOS, Android, Windows Phone, Laptop & Desktop\\n and TV",
        "url": "https://mockuphone.com/"
      }
    ]
  },
  {
    "name": "HTML & CSS Templates ",
    "list": [{
        "Website": "HTML5Up",
        "Description": "Very modern, unique responsive HTML5/CSS3 themes",
        "url": "https://html5up.net/"
      },
      {
        "Website": "Templatemo",
        "Description": "Minimal, resume, gallery themes and more",
        "url": "https://templatemo.com/"
      },
      {
        "Website": "Templated.co",
        "Description": "Tons of minimalistic HTML5/CSS3 themes",
        "url": "https://templated.co/"
      },
      {
        "Website": "FreeHTML5",
        "Description": "Free & premium HTML5 and Bootstrap themes",
        "url": "https://freehtml5.co/"
      },
      {
        "Website": "StyleShout",
        "Description": "Brilliantly crafted free website templates",
        "url": "https://www.styleshout.com/free-templates/"
      },
      {
        "Website": "Start Bootstrap",
        "Description": "Bootstrap starter themes",
        "url": "https://startbootstrap.com/"
      },
      {
        "Website": "Zerotheme",
        "Description": "HTML5, Bootstrap, Prestashop templates",
        "url": "https://www.zerotheme.com/"
      },
      {
        "Website": "HTML5xCSS3",
        "Description": "Collection of wonderful templates in different categories",
        "url": "https://www.html5xcss3.com/"
      },
      {
        "Website": "Colorlib",
        "Description": "Almost any category of theme you can think of",
        "url": "https://colorlib.com/wp/templates/"
      },
      {
        "Website": "Free\\n CSS",
        "Description": "Huge collection of free templates",
        "url": "https://www.free-css.com/free-css-templates"
      },
      {
        "Website": "Hubspot",
        "Description": "Templates, infographics, banners and much more",
        "url": "https://www.hubspot.com/resources"
      },
      {
        "Website": "Mobirise",
        "Description": "Great looking HTML5/CSS3 templates",
        "url": "https://mobirise.com/html-templates/"
      },
      {
        "Website": "Bootswatch",
        "Description": "Free themes for Bootstrap",
        "url": "https://bootswatch.com/"
      },
      {
        "Website": "Onepagelove",
        "Description": "One page websites, templates and resources",
        "url": "https://onepagelove.com/"
      },
      {
        "Website": "Themes For App",
        "Description": "Free Bootstrap themes and landing pages",
        "url": "https://themesfor.app/"
      },
      {
        "Website": "BootstrapTaste",
        "Description": "Premium & Free Bootstrap Templates",
        "url": "https://bootstraptaste.com/"
      },
      {
        "Website": "BootstrapMade",
        "Description": "Elegant, clean and beautiful free templates using Bootstrap.",
        "url": "https://bootstrapmade.com/"
      },
      {
        "Website": "W3Layouts",
        "Description": "W3Layouts: 3784+ Free Website Templates for 2020",
        "url": "https://w3layouts.com/"
      },
      {
        "Website": "Tooplate",
        "Description": "Tooplate: Free HTML Templates for everyone!",
        "url": "https://www.tooplate.com/"
      },
      {
        "Website": "Cruip",
        "Description": "Fully coded HTML templates to help you easily build your startup landing page without hassles.",
        "url": "https://cruip.com/free-templates/"
      },
      {
        "Website": "Shade",
        "Description": "Get High Converting Landing Pages For Free!",
        "url": "https://grayic.com/shade/"
      }
    ]
  },
  {
    "name": "CSS Frameworks",
    "list": [{
        "Website": "Tailwind CSS",
        "Description": "Low level, utility-first framework",
        "url": "https://tailwindcss.com/"
      },
      {
        "Website": "Bootstrap",
        "Description": "Popular UI framework with tons of components that use both CSS and JS",
        "url": "https://getbootstrap.com/"
      },
      {
        "Website": "Materialize",
        "Description": "A modern responsive front-end framework based on Material Design",
        "url": "https://materializecss.com/"
      },
      {
        "Website": "Material Design Lite",
        "Description": "Light framework based on Material Design. No JS dependency",
        "url": "https://getmdl.io/"
      },
      {
        "Website": "Bulma",
        "Description": "Modern CSS framework with no JS",
        "url": "https://bulma.io/"
      },
      {
        "Website": "Skeleton",
        "Description": "Extremely light framework for basic UI elements",
        "url": "http://getskeleton.com/"
      },
      {
        "Website": "Semantic UI",
        "Description": "Empowers designers and developers by creating a shared vocabulary for UI",
        "url": "https://semantic-ui.com/"
      },
      {
        "Website": "Fomantic UI",
        "Description": "A community fork of Semantic-UI",
        "url": "https://fomantic-ui.com/"
      },
      {
        "Website": "Foundation",
        "Description": "Mobile first framework with clean markup",
        "url": "https://get.foundation/"
      },
      {
        "Website": "Pure CSS",
        "Description": "A set of small, responsive CSS modules",
        "url": "https://purecss.io/"
      },
      {
        "Website": "UIKit",
        "Description": "Lightweight and modular front-end framework",
        "url": "https://getuikit.com/"
      },
      {
        "Website": "Susy",
        "Description": "Lightweight, grid-layout engine for Sass",
        "url": "https://www.oddbird.net/susy/"
      },
      {
        "Website": "Milligram.io",
        "Description": "Minimalist CSS framework",
        "url": "https://milligram.io/"
      },
      {
        "Website": "Vanilla Framework",
        "Description": "Simple, extensible CSS framework written in Sass",
        "url": "https://vanillaframework.io/"
      },
      {
        "Website": "Spectre\\n CSS",
        "Description": "Lightweight, modern CSS framework",
        "url": "https://picturepan2.github.io/spectre/"
      },
      {
        "Website": "Picnic CSS",
        "Description": "Lightweight and beautiful library",
        "url": "https://picnicss.com/"
      },
      {
        "Website": "Wing",
        "Description": "A beautiful CSS framework designed for minimalists",
        "url": "https://kbrsh.github.io/wing/"
      },
      {
        "Website": "Chota",
        "Description": "A micro (~3kb) CSS framework",
        "url": "https://jenil.github.io/chota/"
      },
      {
        "Website": "Blueprint CSS",
        "Description": "A lightweight layout library for building great responsive mobile first UIs that work\\n everywhere",
        "url": "https://blueprintcss.dev/"
      },
      {
        "Website": "W3.CSS",
        "Description": "A modern CSS framework with support for desktop, tablet, and mobile design by default.\\n Designed to be independent of jQuery or any other JavaScript library",
        "url": "https://www.w3schools.com/w3css/"
      },
      {
        "Website": "98.css",
        "Description": "A design system for building faithful recreations of old UIs",
        "url": "https://jdan.github.io/98.css/"
      },
      {
        "Website": "NES CSS",
        "Description": "NES-style CSS Framework",
        "url": "https://nostalgic-css.github.io/NES.css/"
      },
      {
        "Website": "Shoelace.css",
        "Description": "Lightweight, forward-thinking CSS library built with future CSS syntax",
        "url": "https://www.shoelace.style/"
      },
      {
        "Website": "MVP.css",
        "Description": "A minimalist stylesheet for HTML elements. No class names, no frameworks, just semantic HTML\\n and you're done",
        "url": "https://andybrewer.github.io/mvp/"
      },
      {
        "Website": "Blaze.css",
        "Description": "Open source modular CSS toolkit providing great structure for building websites quickly",
        "url": "http://blazecss.com/"
      },
      {
        "Website": "Turret CSS",
        "Description": "Turret CSS is a styles framework for development of responsive websites.",
        "url": "https://turretcss.com/"
      },
      {
        "Website": "Cutestrap",
        "Description": "A strong, independent CSS Framework.",
        "url": "https://www.cutestrap.com/"
      },
      {
        "Website": "Shorthand",
        "Description": "Shorthand is a free and open source css framework, that allows you to make unique and modern\\n design without writing any css",
        "url": "https://shorthandcss.com/"
      },
      {
        "Website": "XP.css",
        "Description": "XP.css is an extention of 98.css. A CSS library for building interfaces that look like old\\n UIs.",
        "url": "https://botoxparty.github.io/XP.css/"
      },
      {
        "Website": "Framework7",
        "Description": "Framework7 - is a free and open source framework to develop mobile, desktop or web apps with\\n native look and feel.",
        "url": "https://framework7.io/"
      }
    ]
  },
  {
    "name": "CSS Animations",
    "list": [{
        "Website": "Animate.css",
        "Description": "Just-add-water CSS animations",
        "url": "https://animate.style/"
      },
      {
        "Website": "Bounce.js",
        "Description": "Bounce.js is a tool and JS library that lets you create beautiful CSS3 powered animations",
        "url": "http://bouncejs.com/"
      },
      {
        "Website": "Anime.js",
        "Description": "Anime.js (/ˈæn.ə.meɪ/) is a lightweight JavaScript animation library with a simple, yet\\n powerful API. It works with CSS properties, SVG, DOM attributes and JavaScript Objects",
        "url": "https://animejs.com/"
      },
      {
        "Website": "Magic\\n Animations",
        "Description": "Animations has been one of the most impressive animation libraries available",
        "url": "https://www.minimamente.com/project/magic/"
      },
      {
        "Website": "Zdog",
        "Description": "Round, flat, designer-friendly pseudo-3D engine for canvas & SVG",
        "url": "https://zzz.dog/"
      },
      {
        "Website": "CSShake",
        "Description": "CSShake delivers exactly what it says on the box — a CSS library designed specifically for\\n shaking elements within your web page",
        "url": "http://elrumordelaluz.github.io/csshake/"
      },
      {
        "Website": "Hover.css",
        "Description": "Hover.css is a CSS animation library designed for use with buttons and other UI elements in\\n your website",
        "url": "http://ianlunn.github.io/Hover/"
      },
      {
        "Website": "AniJS",
        "Description": "AniJS is an animation library that allows you to add animations to elements in a simple\\n ‘sentence-like’ structure",
        "url": "http://anijs.github.io/"
      },
      {
        "Website": "Animista",
        "Description": "CSS Animations On Demand",
        "url": "http://animista.net/"
      },
      {
        "Website": "Tachyons-animate",
        "Description": "Tachyons itself is an atomic CSS library with a ton of utility classes for essentially\\n designing anything by adding classes to what you need",
        "url": "https://github.com/anater/tachyons-animate"
      },
      {
        "Website": "Sequence.js",
        "Description": "Sequence.js is a JavaScript library that provides a responsive CSS framework for creating\\n unique sliders, presentations, banners, and other step-based applications",
        "url": "https://www.sequencejs.com/"
      },
      {
        "Website": "Infinite",
        "Description": "These animations, like rotations and pulses, that are specifically designed to run and repeat\\n forever",
        "url": "https://tilomitra.github.io/infinite/"
      },
      {
        "Website": "OBNOXIOUS.CSS",
        "Description": "Animations for the strong of heart, and weak of mind",
        "url": "http://tholman.com/obnoxious/"
      },
      {
        "Website": "MOTION UI",
        "Description": "A Sass library for creating flexible CSS transitions and animations",
        "url": "https://zurb.com/playground/motion-ui"
      }
    ]
  },
  {
    "name": "Javascript Animation Libraries ",
    "list": [{
        "Website": "Greensock",
        "Description": "A JavaScript library for building high-performance animations that work in every major browser",
        "url": "https://greensock.com/"
      },
      {
        "Website": "Velocity.js",
        "Description": "Velocity is an lightweight animation engine with the same API as jQuery's $.animate()",
        "url": "http://velocityjs.org/"
      },
      {
        "Website": "lax.js",
        "Description": "Simple & light weight vanilla javascript plugin to create smooth & beautiful\\n animations when you scroll!",
        "url": "https://github.com/alexfoxy/laxxx"
      },
      {
        "Website": "Rellax.js",
        "Description": "A buttery smooth, super lightweight, vanilla javascript parallax library",
        "url": "https://github.com/dixonandmoe/rellax"
      },
      {
        "Website": "three.js",
        "Description": "An easy to use, lightweight, 3D library with a default WebGL renderer.",
        "url": "https://github.com/mrdoob/three.js/"
      },
      {
        "Website": "wow.js",
        "Description": "Reveal Animations When You Scroll.",
        "url": "https://wowjs.uk/"
      },
      {
        "Website": "chocolat.js",
        "Description": "Free lightbox plugin.",
        "url": "http://chocolat.insipi.de/"
      },
      {
        "Website": "Animate On\\n Scroll",
        "Description": "Animate on scroll library to reveal animations when You scroll.",
        "url": "https://michalsnik.github.io/aos/"
      },
      {
        "Website": "Tilt.Js",
        "Description": "A tiny requestAnimationFrame powered 60+fps lightweight parallax hover tilt effect for jQuery.",
        "url": "http://gijsroge.github.io/tilt.js/"
      }
    ]
  },
  {
    "name": "UI Components & Kits ",
    "list": [{
        "Website": "TagFold",
        "Description": "Useful Bootstrap 4, HTML5, CSS3 Code Snippets to Build Web Layouts",
        "url": "https://tagfold.com/"
      },
      {
        "Website": "UILang",
        "Description": "A minimal, ui-focused programming language for web designers",
        "url": "http://uilang.com/"
      },
      {
        "Website": "Medialoot CSS\\n Components",
        "Description": "Calendars, price grids and other UI components",
        "url": "https://medialoot.com/free-themes/css-components/"
      },
      {
        "Website": "Froala Design\\n Blocks",
        "Description": "Over 170 responsive design blocks ready to be used in your web or mobile apps",
        "url": "https://froala.com/design-blocks"
      },
      {
        "Website": "Material\\n Design For Bootstrap",
        "Description": "Open source toolkit for building material design with Bootstrap",
        "url": "https://fezvrasta.github.io/bootstrap-material-design/"
      },
      {
        "Website": "Photonkit",
        "Description": "Desktop UI library for Electron",
        "url": "http://photonkit.com/"
      },
      {
        "Website": "Flat UI",
        "Description": "Minimal free user interface kit",
        "url": "https://designmodo.github.io/Flat-UI/"
      },
      {
        "Website": "Shards",
        "Description": "A free and modern UI toolkit for web makers based on Bootstrap",
        "url": "https://designrevision.com/downloads/shards/"
      },
      {
        "Website": "Creative Tim",
        "Description": "All types of UI libraries and kits including JS frameworks like React",
        "url": "https://www.creative-tim.com/"
      },
      {
        "Website": "Brumm Shadow Maker",
        "Description": "An online tool to make css shadows",
        "url": "https://brumm.af/shadows"
      },
      {
        "Website": "AdminLTE",
        "Description": "Best open source admin dashboard & control panel theme",
        "url": "https://adminlte.io/"
      },
      {
        "Website": "SpinKit",
        "Description": "Simple CSS Spinners",
        "url": "https://tobiasahlin.com/spinkit/"
      },
      {
        "Website": "Epic Spinners",
        "Description": "CSS spinners collection with Vue.js integration.",
        "url": "https://epic-spinners.epicmax.co/"
      },
      {
        "Website": "Loading.io",
        "Description": "Online service provider for creating simple animations, spinners, progress bar and more",
        "url": "https://loading.io/"
      },
      {
        "Website": "Moving\\n Letters",
        "Description": "Animated Text with JavaScript and anime.js",
        "url": "https://tobiasahlin.com/moving-letters/"
      },
      {
        "Website": "CSS Layout",
        "Description": "A collection of popular web layouts and patterns in pure CSS",
        "url": "https://csslayout.io/"
      },
      {
        "Website": "Codyhouse",
        "Description": "Kick-start your web projects with CodyHouse's front-end framework and library of accessible\\n HTML, CSS, JavaScript components",
        "url": "https://codyhouse.co/"
      },
      {
        "Website": "Tailwind Starter Kit",
        "Description": "Tailwind Starter Kit a beautiful extension for TailwindCSS, Free and Open Source",
        "url": "https://github.com/creativetimofficial/tailwind-starter-kit"
      },
      {
        "Website": "Tailwindtoolbox",
        "Description": "Open source starter templates and components, a plugins directory and useful tools/utilities\\n to kick start your Tailwind CSS project.",
        "url": "https://www.tailwindtoolbox.com/"
      },
      {
        "Website": "tailwindcomponents",
        "Description": "A free repository for community components using TailwindCSS",
        "url": "https://tailwindcomponents.com/"
      },
      {
        "Website": "sweetalert",
        "Description": "SweetAlert makes popup messages easy and pretty.",
        "url": "https://sweetalert.js.org/"
      },
      {
        "Website": "sweetalert2",
        "Description": "A beautiful,responsive,customizable,accessible replacement for javascript's popup boxes",
        "url": "https://sweetalert2.github.io/"
      },
      {
        "Website": "tailblocks",
        "Description": "Open source ready-to-use Tailwind CSS components.",
        "url": "https://mertjf.github.io/tailblocks/"
      }
    ]
  },
  {
    "name": "Design Systems & Style Guides ",
    "list": [{
        "Website": "Material Design",
        "Description": "Google's Material Design",
        "url": "https://material.io/"
      },
      {
        "Website": "Ant Design",
        "Description": "Design system for enterprise-level products",
        "url": "https://ant.design/"
      },
      {
        "Website": "Apple\\n Design\\n Resources",
        "Description": "Guides and templates for using Apple design and UI",
        "url": "https://developer.apple.com/design/resources/"
      },
      {
        "Website": "Primer",
        "Description": "Design, build, and create with GitHub’s design system",
        "url": "https://primer.style/"
      },
      {
        "Website": "Alta\\n UI",
        "Description": "Oracle's design system and toolkit",
        "url": "https://www.oracle.com/webfolder/ux/middleware/alta/index.html"
      },
      {
        "Website": "Pulse",
        "Description": "Design system, guides and React component library",
        "url": "https://pulse.heartbeat.ua/"
      },
      {
        "Website": "Bolt",
        "Description": "Robust Twig and web component powered UI components",
        "url": "https://boltdesignsystem.com/"
      },
      {
        "Website": "Clarity Design System",
        "Description": "UX guidelines, HTML/CSS framework, and Angular components",
        "url": "https://clarity.design/"
      },
      {
        "Website": "AtlasKit",
        "Description": "Atlassian's official UI library, built according to the Atlassian Design Guidelines",
        "url": "https://atlaskit.atlassian.com/"
      },
      {
        "Website": "Audi Design Resources",
        "Description": "Audi UI design system and toolkit",
        "url": "https://www.audi.com/ci/en/guides/user-interface/introduction.html"
      },
      {
        "Website": "Carbon Design\\n Systems",
        "Description": "Carbon is IBM’s open-source design system for products and experiences",
        "url": "https://www.carbondesignsystem.com/"
      },
      {
        "Website": "Yelp Style Guide",
        "Description": "Yelp style guide, components and toolkit",
        "url": "https://www.yelp.com/styleguide"
      },
      {
        "Website": "Comet",
        "Description": "Scalable design system of visual language, components, and design assets",
        "url": "https://comet.discoveryeducation.com/"
      },
      {
        "Website": "ETrade Design System",
        "Description": "Guides and toolkits that blend finance with simplicity and ease of use",
        "url": "https://etrade.design/"
      },
      {
        "Website": "Fundamental\\n Library",
        "Description": "Open source and community driven project for consistent user interfaces",
        "url": "https://sap.github.io/fundamental-styles/"
      },
      {
        "Website": "Infor Design",
        "Description": "Guidelines and resources to create meaningful experiences for Infor’s products",
        "url": "https://design.infor.com/"
      },
      {
        "Website": "Lexicon",
        "Description": "An experience language for crafting beautiful UI",
        "url": "https://liferay.design/lexicon/"
      },
      {
        "Website": "Mailchimp\\n UI/UX",
        "Description": "Style guide and components from Mailchimp",
        "url": "https://ux.mailchimp.com/patterns/color"
      },
      {
        "Website": "Marvel Style\\n Guide",
        "Description": "Set of design principles and components",
        "url": "https://marvelapp.com/styleguide/overview/introduction"
      },
      {
        "Website": "Microsoft Fluent\\n UI",
        "Description": "Collection of UX frameworks from Microsoft",
        "url": "https://developer.microsoft.com/en-us/fluentui#/"
      },
      {
        "Website": "Pluralsight\\n Design System",
        "Description": "Design guide with components for designing with Pluralsight",
        "url": "https://design-system.pluralsight.com/"
      },
      {
        "Website": "Polaris",
        "Description": "Design system that creates great experiences for all of Shopify’s merchants",
        "url": "https://polaris.shopify.com/"
      },
      {
        "Website": "Mozilla Protocol",
        "Description": "Protocol is a design system for Mozilla and Firefox websites",
        "url": "https://protocol.mozilla.org/"
      },
      {
        "Website": "SendGrid Style\\n Guide",
        "Description": "UI library for developing consistent UI/UX at SendGrid",
        "url": "http://styleguide.sendgrid.com/"
      },
      {
        "Website": "VTEX Styleguide",
        "Description": "Reusable patterns, components and assets related to product design in VTEX",
        "url": "https://styleguide.vtex.com/"
      },
      {
        "Website": "Rizzo",
        "Description": "Style guide with UI components, JS components, widgets, etc",
        "url": "https://rizzo.lonelyplanet.com/styleguide/design-elements"
      },
      {
        "Website": "Atomize",
        "Description": "UI framework that helps developers collaborate with designers and build consistent user\\n interfaces effortlessly",
        "url": "https://atomizecode.com/"
      },
      {
        "Website": "StyleGuides.io",
        "Description": "A directory of 500+ styleguides",
        "url": "http://styleguides.io/"
      },
      {
        "Website": "Done\\n Design\\n System",
        "Description": "Open source design system, guides & components",
        "url": "https://uilibrary.github.io/done-design-system/"
      },
      {
        "Website": "Skoda Brand\\n System",
        "Description": "Design guideline for developing applications under the Skoda brand",
        "url": "https://skoda-brand.com/explore-our-brand"
      },
      {
        "Website": "Spectrum",
        "Description": "Adobe’s design system that provides components and tools to help product teams work more\\n efficiently, and to make Adobe’s applications more cohesive.",
        "url": "https://spectrum.adobe.com/"
      }
    ]
  },
  {
    "name": "Online Design Tools ",
    "list": [{
        "Website": "Figma",
        "Description": "Online graphic design tool (Free & paid options)",
        "url": "https://www.figma.com/graphic-design-tool/"
      },
      {
        "Website": "Vectr",
        "Description": "Free vector graphics software",
        "url": "https://vectr.com/"
      },
      {
        "Website": "Canva",
        "Description": "Create beautiful designs (Free & Paid)",
        "url": "https://www.canva.com/"
      },
      {
        "Website": "Get Waves",
        "Description": "A free SVG wave generator to make unique SVG waves for web design",
        "url": "https://getwaves.io/"
      },
      {
        "Website": "Clippy",
        "Description": "Easy CSS clip-path maker",
        "url": "https://bennettfeely.com/clippy/"
      },
      {
        "Website": "Fancy Border Radius",
        "Description": "Eight values specifying border-radius in CSS ( border-radius generator )",
        "url": "https://9elements.github.io/fancy-border-radius/full-control.html"
      },
      {
        "Website": "Wireframe.cc",
        "Description": "Wireframing tool (free & paid)",
        "url": "https://wireframe.cc/"
      },
      {
        "Website": "Fotor",
        "Description": "Photo editor and design maker",
        "url": "https://www.fotor.com/"
      },
      {
        "Website": "Pixlr",
        "Description": "Online photo editor",
        "url": "https://www.pixlr.com/"
      },
      {
        "Website": "Animoto\\n Video Maker",
        "Description": "Make videos online",
        "url": "https://animoto.com/apps/online-video-maker"
      },
      {
        "Website": "RemoveBG",
        "Description": "Remove image backgrounds",
        "url": "https://www.remove.bg/"
      },
      {
        "Website": "Photo Creator",
        "Description": "Create your own photos instead of searching for stock",
        "url": "https://photos.icons8.com/creator"
      },
      {
        "Website": "Visme",
        "Description": "Create presentations, infographics and more",
        "url": "https://www.visme.co/"
      },
      {
        "Website": "Infogram",
        "Description": "Create infograms",
        "url": "https://infogram.com/"
      },
      {
        "Website": "ChartGo",
        "Description": "Create charts and graphs online",
        "url": "https://www.chartgo.com/"
      },
      {
        "Website": "Cartoon Photo",
        "Description": "Turn photos into cartoons",
        "url": "https://cartoon.pho.to/"
      },
      {
        "Website": "Logo Maker",
        "Description": "Create custom logos",
        "url": "https://logomakr.com/"
      },
      {
        "Website": "Whimsical",
        "Description": "Wireframes, diagrams and more (4 free)",
        "url": "https://whimsical.com/"
      },
      {
        "Website": "Whiteboard",
        "Description": "Online drawing tool",
        "url": "https://witeboard.com/"
      },
      {
        "Website": "Octopus",
        "Description": "Sitemap builder",
        "url": "https://octopus.do/"
      },
      {
        "Website": "CTA\\n Button Maker",
        "Description": "Create call to action buttons",
        "url": "https://www.clickminded.com/button-generator/"
      },
      {
        "Website": "Blobmaker",
        "Description": "Blobmaker is a free generative design tool, to help you quickly create random, unique, and\\n organic-looking SVG shapes",
        "url": "https://www.blobmaker.app/"
      },
      {
        "Website": "Personas",
        "Description": "A playful avatar generator for the modern age",
        "url": "https://personas.draftbit.com/"
      },
      {
        "Website": "SoftUI",
        "Description": "A Soft UI (neumorphism) CSS generator",
        "url": "https://www.softui.io"
      },
      {
        "Website": "Photopea",
        "Description": "A Online Photoshop editor",
        "url": "https://www.photopea.com"
      },
      {
        "Website": "Excalidraw",
        "Description": "Virtual whiteboard for sketching hand-drawn like diagrams",
        "url": "https://excalidraw.com/"
      },
      {
        "Website": "Diagrams",
        "Description": "Diagram software and Flowchart maker",
        "url": "https://www.diagrams.net/"
      },
      {
        "Website": "MapInSeconds",
        "Description": "Simple way to visualize your data with a map",
        "url": "http://mapinseconds.com/"
      },
      {
        "Website": "Grid Malven",
        "Description": "A css grid cheatsheet to reference when creating a css grid",
        "url": "http://grid.malven.co/"
      },
      {
        "Website": "Flex Malven",
        "Description": "A flexbox grid cheatsheet to reference when working with flexbox",
        "url": "http://flexbox.malven.co/"
      },
      {
        "Website": "Smart Upscaler",
        "Description": "Upscale images by 2-4x resolution",
        "url": "https://icons8.com/upscaler"
      },
      {
        "Website": "GetAvataaars",
        "Description": "Fun and Colorful free avatars web generator tool by Fang-Pen Lin using Pablo Stanley sketch\\n library",
        "url": "https://getavataaars.com/"
      },
      {
        "Website": "Webflow",
        "Description": "Break the code barrier, Build better business websites, faster. Without coding.",
        "url": "https://webflow.com/"
      },
      {
        "Website": "Trace",
        "Description": "Instantly remove the background from your photos",
        "url": "https://stickermule.com/trace"
      },
      {
        "Website": "Neumorphism.io",
        "Description": "Generate Soft-UI CSS shadow code",
        "url": "https://neumorphism.io/#55b9f3"
      },
      {
        "Website": "DB Designer",
        "Description": "Design your database for free online",
        "url": "https://app.dbdesigner.net/"
      },
      {
        "Website": "Ui Bakery",
        "Description": "Create full-fledged web apps visually",
        "url": "https://uibakery.io/"
      },
      {
        "Website": "Faux",
        "Description": "Turn real code into faux code",
        "url": "http://knutsynstad.com/fauxcode/"
      },
      {
        "Website": "Rive",
        "Description": "Real-time interactive design tool that allows you to design, animate, and immediately\\n integrate your assets into any platform.",
        "url": "https://rive.app/"
      },
      {
        "Website": "Unscreen",
        "Description": "Remove Video Background 100% Automatically and Free",
        "url": "https://www.unscreen.com/"
      },
      {
        "Website": "Kodeshot",
        "Description": "Convert your source code into nice pictures for your articles, tweets, messages, posts...",
        "url": "https://www.kodeshot.net/"
      },
      {
        "Website": "Wix",
        "Description": "Create a Website You’re Proud Of",
        "url": "https://www.wix.com/"
      },
      {
        "Website": "GTmetrix",
        "Description": "Website Speed and Performance Optimization",
        "url": "https://gtmetrix.com/"
      }
    ]
  },
  {
    "name": "Design Inspiration ",
    "list": [{
        "Website": "Behance",
        "Description": "Design projects featured by different creators",
        "url": "https://www.behance.net/"
      },
      {
        "Website": "Dribbble",
        "Description": "Design projects featured by different creators",
        "url": "https://dribbble.com/"
      },
      {
        "Website": "Httpster",
        "Description": "Showcases websites made by people from all over the world",
        "url": "https://httpster.net/2020/apr/"
      },
      {
        "Website": "Microcopy\\n Inspirations",
        "Description": "Curated collection of UX writing examples, microcopy examples and copywriting examples",
        "url": "https://www.microcopyinspirations.com/"
      },
      {
        "Website": "Inspofinds",
        "Description": "Latest design work from designers and the design community",
        "url": "https://inspofinds.com/"
      },
      {
        "Website": "Design Notes",
        "Description": "Free online resource library for product designers",
        "url": "https://www.designnotes.co/"
      },
      {
        "Website": "Land Book",
        "Description": "Displays a large collection of websites to help find inspiration",
        "url": "https://land-book.com/"
      },
      {
        "Website": "Frontend Mentor",
        "Description": "Real-world UI Challenges using HTML, CSS and Javascript",
        "url": "https://www.frontendmentor.io/"
      },
      {
        "Website": "Awwwards",
        "Description": "A website that rate and collects the best websites in the world in UI",
        "url": "https://www.awwwards.com/"
      },
      {
        "Website": "Codrops",
        "Description": "A website that collects the best UI ideas and patterns and make tutorials of it",
        "url": "https://tympanus.net/codrops/"
      },
      {
        "Website": "SaaS Landing Page",
        "Description": "Discover the best landing page examples created by top-class SaaS companies",
        "url": "https://saaslandingpage.com/"
      },
      {
        "Website": "Pages.xyz",
        "Description": "Curate and discover the best designed web pages",
        "url": "https://www.pages.xyz/"
      },
      {
        "Website": "UI Movement",
        "Description": "UI Movement is a community of design enthusiasts who share and discuss the most interesting\\n and unique UI designs",
        "url": "https://uimovement.com/"
      },
      {
        "Website": "lapa ninja",
        "Description": "Best landing page inspiration",
        "url": "https://www.lapa.ninja/"
      },
      {
        "Website": "Freefrontend",
        "Description": "Free front end design from css html and javascript. latest work some design part",
        "url": "https://freefrontend.com/"
      },
      {
        "Website": "Webframe",
        "Description": "Discover and be inspired by beautiful webapp designs",
        "url": "https://webframe.xyz"
      },
      {
        "Website": "Collect UI",
        "Description": "Daily inspiration collected from daily ui archive and beyond. Hand picked, and updating daily.",
        "url": "http://collectui.com/"
      },
      {
        "Website": "Graphic Burger",
        "Description": "A site offering a free and pain icons, mock-ups, Ui-Kits, text effect and backgrounds. This\\n site's resource are a mix of free and paid resources. Icons is on a mix of PNG, SVG, EPS and\\n Sketch Format. Some resources are confusing as there are sponsored content in the middle of the\\n free sets.",
        "url": "https://graphicburger.com/"
      },
      {
        "Website": "Really Good Emails",
        "Description": "A site offering users a ton of company e-mails from customer service to marketing.",
        "url": "https://reallygoodemails.com/"
      },
      {
        "Website": "Free Design\\n Resource",
        "Description": "A site offering fonts, mockups, templates graphics and ui kits.",
        "url": "https://freedesignresources.net/"
      },
      {
        "Website": "Site Inspire",
        "Description": "siteInspire is a showcase of the finest web and interactive design.",
        "url": "https://www.siteinspire.com/"
      },
      {
        "Website": "Web Design\\n Inspiration",
        "Description": "A site for web design inspiration, updated daily.",
        "url": "https://www.webdesign-inspiration.com/"
      },
      {
        "Website": "NavNav",
        "Description": "Responsive navigation examples",
        "url": "https://navnav.co/"
      }
    ]
  },
  {
    "name": "Image Compression ",
    "list": [{
        "Website": "TinyPNG",
        "Description": "Smart PNG and JPEG compression",
        "url": "https://tinypng.com/"
      },
      {
        "Website": "Optimizilla",
        "Description": "Online JPEG and PNG optimizer / compressor with settings and archive download",
        "url": "https://imagecompressor.com/"
      },
      {
        "Website": "Compressor.io",
        "Description": "JPEG, PNG, GIF, SVG Compression",
        "url": "https://compressor.io/"
      },
      {
        "Website": "Squoosh.app",
        "Description": "Image compression from Google Chrome Labs",
        "url": "https://squoosh.app/"
      },
      {
        "Website": "BulkResizePhotos",
        "Description": "Bulk image resizing, compression & converting that perform all the tasks within the\\n browser (It works offline)",
        "url": "https://bulkresizephotos.com/"
      },
      {
        "Website": "iLoveIMG",
        "Description": "The fastest free web app for easy image modification",
        "url": "https://www.iloveimg.com/"
      },
      {
        "Website": "SvgOMG",
        "Description": "Online SVG optimizer with a lot of settings and possibility to cut and paste svg code directly\\n in it.",
        "url": "https://jakearchibald.github.io/svgomg/"
      },
      {
        "Website": "CompressJPEG",
        "Description": "Compress JPEG images with size even greater than 5MB",
        "url": "https://compressjpeg.com/"
      },
      {
        "Website": "CompressNow",
        "Description": "JPEG, GIF, PNG Compression",
        "url": "https://compressnow.com/"
      },
      {
        "Website": "Promo Image Resizer",
        "Description": "Free Image and Photo Resizer",
        "url": "https://compressnow.com/"
      },
      {
        "Website": "Image Optimizer",
        "Description": "Image Optimizer Free With Quality Options",
        "url": "http://www.imageoptimizer.net/"
      },
      {
        "Website": "SVGminify",
        "Description": "This tool removes superfluous information, thereby reducing the size of your SVG files",
        "url": "https://www.svgminify.com/"
      },
      {
        "Website": "JPEG Optimizer",
        "Description": "Free online tool for resizing and compressing digital photos and images for displaying on the\\n web",
        "url": "http://jpeg-optimizer.com/"
      }
    ]
  },
  {
    "name": "Others",
    "list": [{
        "Website": "everysize.kibalabs.com",
        "Description": "Check your awesome responsive webpage looks great in every size",
        "url": "https://everysize.kibalabs.com/"
      },
      {
        "Website": "Devhints.io",
        "Description": "This is a modest collection of cheatsheets on Internet",
        "url": "https://devhints.io/"
      },
      {
        "Website": "The Web Toolbox",
        "Description": "A collection of handy, free-to-use tools for web developers, programmers and designers.",
        "url": "https://thewebtoolbox.cc/"
      },
      {
        "Website": "WebDevTrick",
        "Description": "A famous blog for many amazing HTML, CSS, JQuery designs.",
        "url": "https://webdevtrick.com/"
      },
      {
        "Website": "css-tricks",
        "Description": "Free CSS tricks and some unique ideas for beginners and advanced",
        "url": "https://css-tricks.com/"
      },
      {
        "Website": "Material\\n Design Resizer",
        "Description": "An interactive viewer that helps designers test material design breakpoints across desktop,\\n mobile, and tablet",
        "url": "https://material.io/resources/resizer/"
      },
      {
        "Website": "Nodesign.dev",
        "Description": "A collection of tools for developers who have little to no artistic talent",
        "url": "https://nodesign.dev"
      },
      {
        "Website": "A11ygator",
        "Description": "A web tool to scan websites against WCAG rules",
        "url": "https://a11ygator.chialab.io/"
      },
      {
        "Website": "Commitizen",
        "Description": "Command line tool to formatted commit messages according to the standards",
        "url": "http://commitizen.github.io/cz-cli/"
      },
      {
        "Website": "CleanCss",
        "Description": "Tool For Code Foramtter, Minifier, File Converter",
        "url": "https://www.cleancss.com/"
      },
      {
        "Website": "Tiny helpers",
        "Description": "A collection of free single-purpose online tools for web developers",
        "url": "https://tiny-helpers.dev/"
      },
      {
        "Website": "CSS\\n Ribbon\\n Generator",
        "Description": "This generator will assist in creating a pure CSS corner ribbon.",
        "url": "https://www.cssportal.com/css-ribbon-generator/"
      },
      {
        "Website": "Can I Use",
        "Description": "Check cross-browser compatibility of frontend technologies.",
        "url": "https://caniuse.com/"
      },
      {
        "Website": "kangax-js-compat-table",
        "Description": "Check JavaScript versions (ES5, ES6, ES2016+ etc.) compatibility across different compilers,\\n servers/runtimes and platforms (Desktop and Mobile).",
        "url": "https://kangax.github.io/compat-table/es6/"
      },
      {
        "Website": "mydevice.io",
        "Description": "Most commonly used device resolutions including phones and tablets",
        "url": "https://www.mydevice.io/"
      },
      {
        "Website": "Codepen",
        "Description": "Build, test and discover frontend code.",
        "url": "https://codepen.io/"
      },
      {
        "Website": "Responsively",
        "Description": "A tool for designers and frontend developers to design and debug their in all platforms with\\n ease",
        "url": "https://manojvivek.github.io/responsively-app/"
      },
      {
        "Website": "html2pdf.js",
        "Description": "Client-side HTML-to-PDF rendering using pure JS.",
        "url": "https://ekoopmans.github.io/html2pdf.js/"
      },
      {
        "Website": "CSS Reference",
        "Description": "A collection of all css properties and definitions in detail",
        "url": "https://cssreference.io/"
      }
    ]
  },
  {
    "name": "All in One",
    "list": [{
        "Website": "allthefreestock",
        "url": "https://allthefreestock.com/"
      },
      {
        "Website": "The stocks (Bulk)",
        "url": "http://thestocks.im/"
      },
      {
        "Website": "tympanus (Bulk)",
        "url": "https://tympanus.net/codrops/"
      },
      {
        "Website": "Best Jquery (Bulk)",
        "url": "https://www.bestjquery.com/"
      },
      {
        "Website": "codyhouse Bulk components",
        "url": "https://codyhouse.co/ds/components"
      },
      {
        "Website": "Free Frontend Bulk components",
        "url": "https://freefrontend.com/"
      }
    ]
  }, {
    "name": "Image Tools",
    "list": [{
      "Website": "image Resize",
      "url": "https://www.birme.net/"
    }]
  }, {
    "name": "Design Assets",
    "list": [{
        "Website": "UI Design Daily (bulk)",
        "url": "https://uidesigndaily.com/"
      },
      {
        "Website": "freebiesbug (bulk)",
        "url": "https://freebiesbug.com/"
      },
      {
        "Website": "collectui Bulk UI components",
        "url": "https://collectui.com/"
      },
      {
        "Website": "sketchappsources",
        "url": "https://www.sketchappsources.com/"
      }
    ]
  }, {
    "name": "Icon Assets",
    "list": [{
        "Website": "CSS icons",
        "url": "https://css.gg/"
      },
      {
        "Website": "Animated icons",
        "url": "https://lordicon.com/"
      },
      {
        "Website": "Font faced icons",
        "url": "http://fontello.com/"
      },
      {
        "Website": "Flat Icons - Bulk",
        "url": "https://www.flaticon.com/"
      },
      {
        "Website": "Ion icons - font faced",
        "url": "https://ionicons.com/"
      },
      {
        "Website": "Material icons - SVG",
        "url": "https://material.io/resources/icons/"
      },
      {
        "Website": "Feather icons - SVG",
        "url": "https://feathericons.com/"
      },
      {
        "Website": "Icons 8 - Bulk",
        "url": "https://icons8.com/icons"
      },
      {
        "Website": "fontastic - Vector Icons",
        "url": "http://fontastic.me/"
      }
    ]
  }, {
    "name": "Image Assets",
    "list": [{
        "Website": "Freepik - Bulk",
        "url": "https://www.freepik.com/"
      },
      {
        "Website": "Unsplash",
        "url": "https://unsplash.com/"
      },
      {
        "Website": "Pexels - Images,Videos",
        "url": "https://www.pexels.com/"
      },
      {
        "Website": "Clean Png",
        "url": "https://www.cleanpng.com/"
      },
      {
        "Website": "Pixabay",
        "url": "https://pixabay.com/"
      },
      {
        "Website": "The mockup - mockups",
        "url": "https://themockup.club/"
      },
      {
        "Website": "Threed - 3D Mockups",
        "url": "https://threed.io/"
      },
      {
        "Website": "Canva",
        "url": "https://www.canva.com/photos/free/"
      },
      {
        "Website": "Stocksnap",
        "url": "https://stocksnap.io/"
      },
      {
        "Website": "Burst - high Resolution",
        "url": "https://burst.shopify.com/"
      },
      {
        "Website": "Free Images - Bulk",
        "url": "https://www.freeimages.com/"
      },
      {
        "Website": "Maxkit - videos free",
        "url": "https://mixkit.co/"
      }
    ]
  }, {
    "name": "Colors Assets",
    "list": [{
        "Website": "Coolors - color pallet",
        "url": "https://coolors.co/"
      },
      {
        "Website": "Flat UI colors - color pallet",
        "url": "https://flatuicolors.com/"
      },
      {
        "Website": "color mind - color pallet",
        "url": "http://colormind.io/"
      },
      {
        "Website": "Gradient animator",
        "url": "https://www.gradient-animator.com/"
      },
      {
        "Website": "Color Gradient Generator",
        "url": "https://mycolor.space/gradient"
      },
      {
        "Website": "Pink Colors",
        "url": "https://picular.co/pink"
      },
      {
        "Website": "brandcolors",
        "url": "http://brandcolors.net/"
      },
      {
        "Website": "Website color finder",
        "url": "http://stylifyme.com/"
      },
      {
        "Website": "colinkeany color gradient",
        "url": "http://colinkeany.com/blend/"
      },
      {
        "Website": "image color picker",
        "url": "https://image-color.com/"
      }
    ]
  }, {
    "name": "Fonts Assets",
    "list": [{
      "Website": "font Fabric",
      "url": "https://www.fontfabric.com/"
    }]
  }, {
    "name": "Backgrounds Assets",
    "list": [{
        "Website": "Transparent Textures",
        "url": "https://www.transparenttextures.com/"
      },
      {
        "Website": "williamngan 3D, Transparent",
        "url": "http://williamngan.github.io/kubist/"
      },
      {
        "Website": "Cool Background",
        "url": "https://coolbackgrounds.io/"
      },
      {
        "Website": "Web Gradients - Gradients",
        "url": "https://webgradients.com/"
      },
      {
        "Website": "FANCY-BORDER-RADIUS",
        "url": "https://9elements.github.io/fancy-border-radius/"
      },
      {
        "Website": "Web Background Animation Effects - Bulk",
        "url": "https://bashooka.com/coding/web-background-animation-effects/"
      },
      {
        "Website": "blobmaker - Bulk",
        "url": "https://www.blobmaker.app/"
      },
      {
        "Website": "svgbackgroundsfb",
        "url": "https://www.svgbackgrounds.com/"
      }
    ]
  }, {
    "name": "Plugins Assets",
    "list": [{
        "Website": "tympanus Sidebar animations, header scroll effects",
        "url": "https://tympanus.net/Development/SidebarTransitions/"
      },
      {
        "Website": "countUp - Numbers Count up",
        "url": "https://inorganik.github.io/countUp.js/"
      },
      {
        "Website": "Page Scroll Animation",
        "url": "https://alvarotrigo.com/pagePiling/"
      },
      {
        "Website": "Scroll Animation",
        "url": "http://scrollme.nckprsn.com/"
      },
      {
        "Website": "Video background -Full video",
        "url": "http://vodkabears.github.io/vide/"
      },
      {
        "Website": "Vfitvidsjs -video Player",
        "url": "http://fitvidsjs.com/"
      },
      {
        "Website": "Video Player",
        "url": "https://redtettemer.github.io/rtop-video-player/"
      },
      {
        "Website": "CSS Lint CSS Error finder",
        "url": "http://csslint.net/"
      },
      {
        "Website": "Isotope - Filter Animation",
        "url": "https://isotope.metafizzy.co/"
      },
      {
        "Website": "Fast Click - Click Event speed improve",
        "url": "https://github.com/ftlabs/fastclick"
      },
      {
        "Website": "typed - Text Typed Animation",
        "url": "https://mattboldt.com/demos/typed-js/"
      },
      {
        "Website": "parallax js",
        "url": "http://pixelcog.github.io/parallax.js/"
      },
      {
        "Website": "photoswipe - Photo viewing",
        "url": "https://photoswipe.com/"
      },
      {
        "Website": "Grid Filter - Sort,search",
        "url": "https://muuri.dev/"
      },
      {
        "Website": "ANCHOR SCROLL",
        "url": "http://www.virgiliudiaconu.com/work/anchor-scroll"
      },
      {
        "Website": "Image Focus Point",
        "url": "http://jonom.github.io/jquery-focuspoint/demos/helper/index.html"
      },
      {
        "Website": "SVG Magic",
        "url": "http://dirkgroenen.nl/SVGMagic/"
      },
      {
        "Website": "Rounded Slider -  counter",
        "url": "https://roundsliderui.com/demos.html"
      },
      {
        "Website": "Multi navigation menu",
        "url": "https://slinky.js.org/"
      },
      {
        "Website": "Fav icon Generator",
        "url": "https://realfavicongenerator.net/"
      }
    ]
  }, {
    "name": "Animation Plugins Assets",
    "list": [{
        "Website": "Anime js - Animation",
        "url": "https://animejs.com/"
      },
      {
        "Website": "SVG js - SVG Animation",
        "url": "https://svgjs.com/docs/3.0/"
      },
      {
        "Website": "AOS - Site scroll Animation",
        "url": "https://michalsnik.github.io/aos/"
      },
      {
        "Website": "Minimamente - CSS animation",
        "url": "https://www.minimamente.com/project/magic/"
      },
      {
        "Website": "blivesta - Jquery animation",
        "url": "http://git.blivesta.com/animsition/"
      },
      {
        "Website": "prinzhorn - scroll animation",
        "url": "http://prinzhorn.github.io/skrollr/"
      },
      {
        "Website": "Hover.CSS - Buttons animation",
        "url": "http://ianlunn.github.io/Hover/"
      },
      {
        "Website": "CSS Loaders - Loaders animation",
        "url": "https://projects.lukehaas.me/css-loaders/"
      },
      {
        "Website": "Scrolling with CSS variables",
        "url": "https://basicscroll.electerious.com/"
      },
      {
        "Website": "CSS Animation",
        "url": "http://cssanimation.io/"
      },
      {
        "Website": "scrolly js",
        "url": "http://scrollyjs.com/"
      },
      {
        "Website": "shapeshifter - SVG animation",
        "url": "https://shapeshifter.design/"
      }
    ]
  }, {
    "name": "CSS Generator",
    "list": [{
        "Website": "CSS3 Generator - CSS3 Generator",
        "url": "http://css3generator.com/"
      },
      {
        "Website": "CSS Arrows - CSS Arrows",
        "url": "http://www.cssarrowplease.com/"
      },
      {
        "Website": "CSS Triangle  - Triangles",
        "url": "http://apps.eky.hk/css-triangle-generator/"
      }
    ]
  }, {
    "name": "Study Material",
    "list": [{
        "Website": "cssreference - CSS Study material",
        "url": "https://cssreference.io/"
      },
      {
        "Website": "Web Code - Bulk",
        "url": "https://webcode.tools/"
      },
      {
        "Website": "material - Bulk",
        "url": "https://material.io/design"
      }
    ]
  }, {
    "name": "Code Formatters",
    "list": [{
        "Website": "codebeautify - Bulk",
        "url": "https://codebeautify.org/"
      },
      {
        "Website": "freeformatter - Bulk",
        "url": "https://www.freeformatter.com/css-beautifier.html"
      },
      {
        "Website": "cleancss",
        "url": "https://www.cleancss.com/css-beautify/"
      }
    ]
  }, {
    "name": "Image Hover Effects / Filter effects",
    "list": [{
        "Website": "Image Hover Effects - bootstrap",
        "url": "https://miketricking.github.io/bootstrap-image-hover/"
      },
      {
        "Website": "Image Filters - CSS image filter",
        "url": "https://www.cssfilters.co/"
      },
      {
        "Website": "Image Filters - Instagram CSS image filter",
        "url": "https://una.im/CSSgram/"
      }
    ]
  }, {
    "name": "Image Editors",
    "list": [{
        "Website": "birme",
        "url": "https://www.birme.net/"
      },
      {
        "Website": "photopea",
        "url": "https://www.photopea.com/"
      },
      {
        "Website": "Image Editors - Bulk",
        "url": "https://www.iloveimg.com/"
      },
      {
        "Website": "pixlr - Bulk",
        "url": "https://pixlr.com/editor/"
      }
    ]
  }, {
    "name": "Spell checker",
    "list": [{
      "Website": "typosaur - Spell checking",
      "url": "https://typosaur.us/"
    }]
  }, {
    "name": "Converters",
    "list": [{
        "Website": "convertio image converter",
        "url": "https://convertio.co/"
      },
      {
        "Website": "convertio Bulk",
        "url": "https://www.jpeg.io/"
      },
      {
        "Website": "CSS to Sass Converter",
        "url": "https://css2sass.herokuapp.com/"
      },
      {
        "Website": "Image converter - Bulk",
        "url": "https://image.online-convert.com/convert-to-webp"
      }
    ]
  }, {
    "name": "Responsive",
    "list": [{
        "Website": "yesviz",
        "url": "https://yesviz.com/"
      },
      {
        "Website": "responsiv",
        "url": "http://responsiv.eu/er.php"
      },
      {
        "Website": "All Devices Responsive",
        "url": "http://www.infobyip.com/testwebsiteresolution.php"
      },
      {
        "Website": "manojvivek",
        "url": "https://manojvivek.github.io/responsively-app/"
      },
      {
        "Website": "material",
        "url": "https://material.io/resources/resizer/"
      },
      {
        "Website": "responsinator",
        "url": "http://www.responsinator.com/"
      },
      {
        "Website": "Find Media Queries for any devices",
        "url": "https://simplecss.eu/"
      }
    ]
  }, {
    "name": "Image Compressor",
    "list": [{
        "Website": "tinyjpg",
        "url": "https://tinyjpg.com/"
      },
      {
        "Website": "compressjpeg",
        "url": "https://compressjpeg.com/"
      },
      {
        "Website": "compressor",
        "url": "https://compressor.io/"
      }
    ]
  }, {
    "name": "Codepen",
    "list": [{
        "Website": "Menu Animated Dropdown With Pure Css",
        "url": "https://codepen.io/bojankrsmanovic/pen/MyXRjQ"
      },
      {
        "Website": "Hamburger",
        "url": "https://codepen.io/ainalem/pen/PoYvggj"
      },
      {
        "Website": "Hamburger",
        "url": "https://codepen.io/ainalem/pen/GeMqdP"
      }
    ]
  }
]